pydevmgr_serial/__init__.py
pydevmgr_serial/device.py
pydevmgr_serial/engine.py
pydevmgr_serial/interface.py
pydevmgr_serial/node.py
pydevmgr_serial/rpc.py
pydevmgr_serial-0.6a0.dist-info/WHEEL
pydevmgr_serial-0.6a0.dist-info/METADATA
pydevmgr_serial-0.6a0.dist-info/RECORD
