Metadata-Version: 2.1
Name: pydevmgr-serial
Version: 0.6a0
Summary: based pydevmgr object for serial communication
License: CECILL-2.1
Author: Sylvain Guieu
Author-email: sylvain.guieu@univ-grenoble-alpes.fr
Requires-Python: >=3.7,<4.0
Classifier: License :: OSI Approved :: CEA CNRS Inria Logiciel Libre License, version 2.1 (CeCILL-2.1)
Classifier: Programming Language :: Python :: 3
Classifier: Programming Language :: Python :: 3.7
Classifier: Programming Language :: Python :: 3.8
Classifier: Programming Language :: Python :: 3.9
Classifier: Programming Language :: Python :: 3.10
Classifier: Programming Language :: Python :: 3.11
Requires-Dist: pydevmgr-core (==0.6.a0)
Requires-Dist: pyserial (>=3.5,<4.0)
